prompt_parser/__init__.py
prompt_parser/attributes.py
prompt_parser/prompt.py
prompt_parser/tool.py
prompt_parser/utils.py
prompt_parser-0.4.0.dist-info/licenses/LICENSE
test/__init__.py
test/test_prompt_parser.py
prompt_parser-0.4.0.dist-info/METADATA
prompt_parser-0.4.0.dist-info/WHEEL
prompt_parser-0.4.0.dist-info/top_level.txt
prompt_parser-0.4.0.dist-info/RECORD
