Metadata-Version: 2.4
Name: prompt_parser
Version: 0.4.0
Summary: A simple Python library for parsing LLM prompts.
Home-page: https://github.com/nank1ro/prompt-parser
Author: Alexandru Mariuti
Author-email: alex@mariuti.com
Project-URL: GitHub, https://github.com/nank1ro/prompt-parser
Project-URL: Changelog, https://github.com/nank1ro/prompt-parser/blob/main/CHANGELOG.md
Classifier: Programming Language :: Python :: 3
Classifier: License :: OSI Approved :: MIT License
Classifier: Operating System :: OS Independent
Requires-Python: >=3.6
License-File: LICENSE
Requires-Dist: pydantic>=2.0.0
Requires-Dist: pyyaml>=6.0.0
Dynamic: author
Dynamic: author-email
Dynamic: classifier
Dynamic: description
Dynamic: description-content-type
Dynamic: home-page
Dynamic: license-file
Dynamic: project-url
Dynamic: requires-dist
Dynamic: requires-python
Dynamic: summary
